segment_torch/__init__.py
segment_torch/attention_unet.py
segment_torch/augment.py
segment_torch/unet.py
segment_torch/utils.py
segment_torch-0.0.10.dist-info/METADATA
segment_torch-0.0.10.dist-info/WHEEL
segment_torch-0.0.10.dist-info/top_level.txt
segment_torch-0.0.10.dist-info/RECORD
