Metadata-Version: 2.1
Name: segment-torch
Version: 0.0.10
Summary: Universal implementation of the UNet architecture for image segmentation.
Home-page: https://github.com/lacykaltgr/agriculture-image-processing
Author: László Freund
Author-email: freundl0509@gmail.com
License: MIT
Keywords: unet,image segmentation,segmentation
Classifier: Development Status :: 3 - Alpha
Classifier: Intended Audience :: Developers
Classifier: Topic :: Software Development :: Build Tools
Classifier: License :: OSI Approved :: MIT License
Classifier: Programming Language :: Python :: 3
Classifier: Programming Language :: Python :: 3.4
Classifier: Programming Language :: Python :: 3.5
Classifier: Programming Language :: Python :: 3.6
Classifier: Programming Language :: Python :: 3.7
Classifier: Programming Language :: Python :: 3.8
Classifier: Programming Language :: Python :: 3.9
Requires-Dist: torch
Requires-Dist: numpy
